README.md
setup.py
bin/read_vme_offline
read_vme_offline/__init__.py
read_vme_offline/asc2df.py
read_vme_offline/cut.py
read_vme_offline/df2spe.py
read_vme_offline/dpp2jpg.py
read_vme_offline/erlang.py
read_vme_offline/general.py
read_vme_offline/nocurses_bar.py
read_vme_offline/rserver.py
read_vme_offline/simple_read.py
read_vme_offline/version.py
read_vme_offline.egg-info/PKG-INFO
read_vme_offline.egg-info/SOURCES.txt
read_vme_offline.egg-info/dependency_links.txt
read_vme_offline.egg-info/requires.txt
read_vme_offline.egg-info/top_level.txt