Metadata-Version: 2.1
Name: read-vme-offline
Version: 0.2.28
Summary: Automatically created environment for python package
Home-page: http://gitlab.com/npicas/read_vme_offline
Author: anastasia_jaromrax
Author-email: ojr@ujf.cas.cz
License: GPL2
Platform: UNKNOWN
